bib2yaml/__init__.py
bib2yaml/bib2yaml.py
bib2yaml-1.0.0.dist-info/WHEEL
bib2yaml-1.0.0.dist-info/METADATA
bib2yaml-1.0.0.dist-info/RECORD
